./.gitignore
./CONTRIBUTING.md
./LICENSE
./PKG-INFO
./README.md
./pyproject.toml
./server.py
./.github/workflows/publish.yml
./.github/workflows/test.yml
./tests/__init__.py
./tests/test_server.py
apple_reminders_mcp-0.1.0.dist-info/METADATA
apple_reminders_mcp-0.1.0.dist-info/WHEEL
apple_reminders_mcp-0.1.0.dist-info/licenses/LICENSE
apple_reminders_mcp-0.1.0.dist-info/RECORD
