Metadata-Version: 2.4
Name: apple-reminders-mcp
Version: 0.1.0
Summary: MCP server for managing Apple Reminders on macOS
Project-URL: Homepage, https://github.com/shreyanshjain05/apple_reminder_mcp_server
Project-URL: Repository, https://github.com/shreyanshjain05/apple_reminder_mcp_server
Project-URL: Issues, https://github.com/shreyanshjain05/apple_reminder_mcp_server/issues
Author-email: Shreyansh Jain <shreyanshjain05@gmail.com>
License-Expression: MIT
License-File: LICENSE
Keywords: ai,apple,applescript,llm,macos,mcp,reminders
Classifier: Development Status :: 4 - Beta
Classifier: Environment :: MacOS X
Classifier: Intended Audience :: Developers
Classifier: License :: OSI Approved :: MIT License
Classifier: Operating System :: MacOS
Classifier: Programming Language :: Python :: 3
Classifier: Programming Language :: Python :: 3.10
Classifier: Programming Language :: Python :: 3.11
Classifier: Programming Language :: Python :: 3.12
Classifier: Topic :: Software Development :: Libraries :: Python Modules
Requires-Python: >=3.10
Requires-Dist: fastmcp>=2.0.0
Requires-Dist: python-dateutil>=2.8.0
Provides-Extra: dev
Requires-Dist: pytest-asyncio>=0.21.0; extra == 'dev'
Requires-Dist: pytest>=7.0.0; extra == 'dev'
